{
  "73a4fcd14cc9766b9b9bfd50b8ca153a": {
    "home": "France",
    "away": "Senegal",
    "home_score": 0,
    "away_score": 0,
    "completed": false,
    "ht_sent": false,
    "updated": "2026-06-16T19:33:19.317447+00:00"
  },
  "espn_760433": {
    "home": "Argentina",
    "away": "Algeria",
    "home_score": 3,
    "away_score": 0,
    "completed": false,
    "ht_sent": true,
    "updated": "2026-06-17T02:46:25.876374+00:00"
  },
  "espn_760435": {
    "home": "Portugal",
    "away": "DR Congo",
    "home_score": 1,
    "away_score": 1,
    "completed": true,
    "ko_sent": false,
    "ht_sent": true,
    "abpfiff_sent": true,
    "scorer_names": [],
    "last_goal_scorer": "",
    "updated": "2026-06-17T19:28:55.918252+00:00"
  },
  "espn_760437": {
    "home": "England",
    "away": "Croatia",
    "home_score": 4,
    "away_score": 2,
    "completed": true,
    "ko_sent": true,
    "ht_sent": true,
    "abpfiff_sent": true,
    "scorer_names": [],
    "last_goal_scorer": "",
    "updated": "2026-06-17T22:19:02.168054+00:00"
  },
  "espn_760434": {
    "home": "Ghana",
    "away": "Panama",
    "home_score": 1,
    "away_score": 0,
    "completed": false,
    "ko_sent": true,
    "ht_sent": true,
    "abpfiff_sent": false,
    "scorer_names": [],
    "last_goal_scorer": "",
    "updated": "2026-06-18T01:00:19.354356+00:00"
  },
  "usa_vs_australia_wm2026": {
    "home": "United States",
    "away": "Australia",
    "home_score": 1,
    "away_score": 0,
    "completed": false,
    "ht_sent": false,
    "updated": "2026-06-19T19:28:38.146557+00:00"
  },
  "espn_760442": {
    "home": "United States",
    "away": "Australia",
    "home_score": 2,
    "away_score": 0,
    "completed": false,
    "ht_sent": true,
    "updated": "2026-06-19T20:53:30.274409+00:00"
  },
  "espn_760444": {
    "home": "Brazil",
    "away": "Haiti",
    "home_score": 3,
    "away_score": 0,
    "completed": false,
    "ht_sent": true,
    "updated": "2026-06-20T02:00:39.685723+00:00"
  },
  "espn_760447": {
    "home": "Netherlands",
    "away": "Sweden",
    "home_score": 5,
    "away_score": 1,
    "completed": false,
    "ht_sent": true,
    "updated": "2026-06-20T18:53:14.120944+00:00"
  },
  "espn_760453": {
    "home": "Spain",
    "away": "Saudi Arabia",
    "home_score": 4,
    "away_score": 0,
    "completed": false,
    "ht_sent": true,
    "updated": "2026-06-21T17:53:13.903082+00:00"
  },
  "espn_760451": {
    "home": "Belgium",
    "away": "Iran",
    "home_score": 0,
    "away_score": 0,
    "completed": false,
    "ht_sent": true,
    "updated": "2026-06-21T20:53:50.277442+00:00"
  },
  "espn_760450": {
    "home": "Uruguay",
    "away": "Cape Verde",
    "home_score": 2,
    "away_score": 2,
    "completed": false,
    "ht_sent": true,
    "updated": "2026-06-21T23:54:16.417391+00:00"
  },
  "espn_760452": {
    "home": "New Zealand",
    "away": "Egypt",
    "home_score": 1,
    "away_score": 0,
    "completed": false,
    "ht_sent": false,
    "updated": "2026-06-22T02:12:19.173825+00:00"
  },
  "espn_760456": {
    "home": "Argentina",
    "away": "Austria",
    "home_score": 1,
    "away_score": 0,
    "completed": false,
    "ht_sent": true,
    "updated": "2026-06-22T18:46:06.852792+00:00"
  },
  "espn_760454": {
    "home": "Norway",
    "away": "Senegal",
    "home_score": 3,
    "away_score": 1,
    "completed": false,
    "ht_sent": true,
    "updated": "2026-06-23T01:51:45.351292+00:00"
  },
  "espn_760461": {
    "home": "Portugal",
    "away": "Uzbekistan",
    "home_score": 5,
    "away_score": 0,
    "completed": false,
    "ht_sent": false,
    "updated": "2026-06-23T18:54:25.414084+00:00"
  },
  "espn_760464": {
    "home": "Morocco",
    "away": "Haiti",
    "home_score": 4,
    "away_score": 2,
    "completed": false,
    "ht_sent": true,
    "updated": "2026-06-24T23:54:52.526420+00:00"
  },
  "espn_760465": {
    "home": "Scotland",
    "away": "Brazil",
    "home_score": 0,
    "away_score": 3,
    "completed": false,
    "ht_sent": true,
    "updated": "2026-06-24T23:54:52.526420+00:00"
  },
  "espn_760466": {
    "home": "South Africa",
    "away": "South Korea",
    "home_score": 1,
    "away_score": 0,
    "completed": false,
    "ht_sent": true,
    "updated": "2026-06-25T02:33:25.418021+00:00"
  },
  "_meta": {
    "heartbeat_at": "2026-07-14T07:55:20Z",
    "reason": "no open bets"
  }
}